osdbinfos/__init__.py
osdbinfos/osdbinfos.py
osdbinfos/version.py
osdbinfos-0.0.12.dist-info/DESCRIPTION.rst
osdbinfos-0.0.12.dist-info/entry_points.txt
osdbinfos-0.0.12.dist-info/METADATA
osdbinfos-0.0.12.dist-info/metadata.json
osdbinfos-0.0.12.dist-info/pbr.json
osdbinfos-0.0.12.dist-info/RECORD
osdbinfos-0.0.12.dist-info/top_level.txt
osdbinfos-0.0.12.dist-info/WHEEL
