Metadata-Version: 2.0
Name: osdbinfos
Version: 0.0.12
Summary: Identify videos files from opensubtitle webservice
Home-page: UNKNOWN
Author: Jc Saad-Dupuy 2015
Author-email: UNKNOWN
License: WTFPL
Keywords: videos files opensubtitle
Platform: UNKNOWN
Requires-Dist: minibelt (>=0.1.1)
